logging_fortified/__init__.py
logging_fortified/logger_adapter_custom.py
logging_fortified/logger_json_lexer.py
logging_fortified/logging.py
logging_fortified/logging_format.py
logging_fortified/logging_json_formatter.py
logging_fortified/logging_levels.py
logging_fortified/logging_output.py
logging_fortified/errors/__init__.py
logging_fortified/errors/errors_traceback.py
logging_fortified/support/__init__.py
logging_fortified/support/singleton.py
logging_fortified-0.1.5.dist-info/METADATA
logging_fortified-0.1.5.dist-info/RECORD
logging_fortified-0.1.5.dist-info/WHEEL
logging_fortified-0.1.5.dist-info/top_level.txt
