Metadata-Version: 2.1
Name: logging-fortified
Version: 0.1.5
Summary: Extension to Python `logging` functionality.
Home-page: https://github.com/jeff00seattle/logging-fortified
Author: UNKNOWN
Author-email: UNKNOWN
License: MIT License
Download-URL: https://github.com/jeff00seattle/logging-fortified/archive/v0.1.5.tar.gz
Keywords: logger logging fortified
Platform: UNKNOWN
Classifier: Development Status :: 5 - Production/Stable
Classifier: Intended Audience :: Developers
Classifier: Natural Language :: English
Classifier: License :: OSI Approved :: MIT License
Classifier: Operating System :: OS Independent
Classifier: Natural Language :: English
Classifier: Programming Language :: Python
Classifier: Programming Language :: Python :: 3
Classifier: Programming Language :: Python :: 3.4
Classifier: Programming Language :: Python :: 3.5
Classifier: Programming Language :: Python :: 3.6
Classifier: Topic :: Software Development :: Libraries :: Python Modules
Requires-Dist: coloredlogs (>=7.3)
Requires-Dist: httpbin (>=0.6.2)
Requires-Dist: python-json-logger (>=0.1.8)
Requires-Dist: pprintpp (>=0.3.0)
Requires-Dist: Pygments (>=2.2.0)
Requires-Dist: pytest (>=3.5.1)
Requires-Dist: pytest-cov (>=2.5.1)
Requires-Dist: pytest-httpbin (>=0.3.0)
Requires-Dist: pytest-mock (>=1.10.0)
Requires-Dist: pytz (>=2018.4)
Requires-Dist: safe-cast (>=0.1.1)
Requires-Dist: tzlocal (>=1.5.1)
Requires-Dist: wheel (>=0.30.0)
